matrice_ifri/__init__.py
matrice_ifri/matrice.py
matrice_ifri-0.1.dist-info/METADATA
matrice_ifri-0.1.dist-info/WHEEL
matrice_ifri-0.1.dist-info/top_level.txt
matrice_ifri-0.1.dist-info/RECORD
