Metadata-Version: 2.1
Name: matrice-ifri
Version: 0.1
Summary: Un simple package pour les calculs matriciels
Home-page: https://github.com/mrcryptsie/matrice_ifri
Author: TITO Lucien
Author-email: titovlucien@gmail.com
Classifier: Programming Language :: Python :: 3
Classifier: License :: OSI Approved :: MIT License
Classifier: Operating System :: OS Independent
Requires-Python: >=3.6
